voxcpm/__init__.py
voxcpm/cli.py
voxcpm/core.py
voxcpm/zipenhancer.py
voxcpm/model/__init__.py
voxcpm/model/utils.py
voxcpm/model/voxcpm.py
voxcpm/modules/__init__.py
voxcpm/modules/audiovae/__init__.py
voxcpm/modules/audiovae/audio_vae.py
voxcpm/modules/layers/__init__.py
voxcpm/modules/layers/lora.py
voxcpm/modules/layers/scalar_quantization_layer.py
voxcpm/modules/locdit/__init__.py
voxcpm/modules/locdit/local_dit.py
voxcpm/modules/locdit/unified_cfm.py
voxcpm/modules/locenc/__init__.py
voxcpm/modules/locenc/local_encoder.py
voxcpm/modules/minicpm4/__init__.py
voxcpm/modules/minicpm4/cache.py
voxcpm/modules/minicpm4/config.py
voxcpm/modules/minicpm4/model.py
voxcpm/training/__init__.py
voxcpm/training/accelerator.py
voxcpm/training/config.py
voxcpm/training/data.py
voxcpm/training/packers.py
voxcpm/training/state.py
voxcpm/training/tracker.py
voxcpm/utils/text_normalize.py
voxcpm-1.5.0.dist-info/licenses/LICENSE
voxcpm-1.5.0.dist-info/METADATA
voxcpm-1.5.0.dist-info/WHEEL
voxcpm-1.5.0.dist-info/entry_points.txt
voxcpm-1.5.0.dist-info/top_level.txt
voxcpm-1.5.0.dist-info/RECORD
